data/configs.json
deployer/__init__.py
deployer/__main__.py
deployer/cli.py
deployer/consts.py
deployer/manipulators/__init__.py
deployer/manipulators/command_manipulator.py
deployer/manipulators/git_manipulator.py
log/.keep
.keep
automatic_deployer-0.3.3.dist-info/entry_points.txt
automatic_deployer-0.3.3.dist-info/WHEEL
automatic_deployer-0.3.3.dist-info/METADATA
automatic_deployer-0.3.3.dist-info/license_files/LICENSE
automatic_deployer-0.3.3.dist-info/RECORD
