Metadata-Version: 2.1
Name: automatic-deployer
Version: 0.3.3
Summary: A CLI App to watch git repo and automatically run a command (deploy command, ex. build and run docker container) after inspecting some changes.
License: MIT
Author-email: Reza Mohammadi <rmm.dev.backend@gmail.com>
Requires-Python: >=3.10
Classifier: Development Status :: 4 - Beta
Classifier: Intended Audience :: Developers
Classifier: Intended Audience :: Information Technology
Classifier: Intended Audience :: System Administrators
Classifier: License :: OSI Approved :: MIT License
Classifier: Operating System :: OS Independent
Classifier: Programming Language :: Python
Classifier: Programming Language :: Python :: 3
Classifier: Programming Language :: Python :: 3 :: Only
Classifier: Programming Language :: Python :: 3.10
Classifier: Topic :: Home Automation
Classifier: Topic :: Software Development
Classifier: Topic :: Software Development :: Version Control
Classifier: Topic :: Software Development :: Version Control :: Git
Classifier: Topic :: System :: Installation/Setup
Classifier: Topic :: Utilities
Requires-Dist: GitPython>=3.1.27
Requires-Dist: typer[all]>=0.6.1
Project-URL: homepage, https://github.com/rmmbdev/automatic-deployer
Project-URL: repository, https://github.com/rmmbdev/automatic-deployer
